{"http://icondataset.org/devil": {"only not cf": ["http://icondataset.org/winged-creature"], "only cf": ["http://icondataset.org/figure", "http://icondataset.org/mors-aeterna", "http://icondataset.org/holding-with-a-hand", "http://icondataset.org/human"], "in both": []}, "http://icondataset.org/tityus": {"only not cf": ["http://icondataset.org/fettered-man"], "only cf": ["http://icondataset.org/man"], "in both": []}, "http://icondataset.org/mars": {"only not cf": ["http://icondataset.org/helmet"], "only cf": ["http://icondataset.org/woman", "http://icondataset.org/hat", "http://icondataset.org/touching-breast", "http://icondataset.org/gentleman", "http://icondataset.org/armor"], "in both": ["http://icondataset.org/backward-turning-movement", "http://icondataset.org/man", "http://icondataset.org/cloak", "http://icondataset.org/shield", "http://icondataset.org/spear"]}, "http://icondataset.org/serapis": {"only not cf": ["http://icondataset.org/woman", "http://icondataset.org/throne", "http://icondataset.org/modius", "http://icondataset.org/sceptre"], "only cf": ["http://icondataset.org/head-of-a-lion", "http://icondataset.org/head-of-a-wolf", "http://icondataset.org/three-headed-serpent", "http://icondataset.org/head-of-a-dog"], "in both": []}, "http://icondataset.org/dieu-amour": {"only not cf": ["http://icondataset.org/bow"], "only cf": ["http://icondataset.org/torch", "http://icondataset.org/tree", "http://icondataset.org/sitting-on"], "in both": ["http://icondataset.org/clothes", "http://icondataset.org/wings", "http://icondataset.org/crown", "http://icondataset.org/arrow", "http://icondataset.org/boy"]}, "http://icondataset.org/hercules": {"only not cf": ["http://icondataset.org/effort", "http://icondataset.org/sphere", "http://icondataset.org/lion-skin", "http://icondataset.org/supporting", "http://icondataset.org/figure", "http://icondataset.org/carrying-on-shoulders"], "only cf": ["http://icondataset.org/powerful-sturdiness", "http://icondataset.org/club", "http://icondataset.org/energy", "http://icondataset.org/forceful"], "in both": ["http://icondataset.org/man", "http://icondataset.org/bow", "http://icondataset.org/drawing-the-bow"]}, "http://icondataset.org/christ": {"only not cf": ["http://icondataset.org/dead-body-of-a-man"], "only cf": ["http://icondataset.org/halo-of-rays", "http://icondataset.org/child", "http://icondataset.org/lifting-one-hand", "http://icondataset.org/cornerstone-of-a-church", "http://icondataset.org/crown", "http://icondataset.org/halo", "http://icondataset.org/sceptre", "http://icondataset.org/ground", "http://icondataset.org/cloth", "http://icondataset.org/condemning-gesture", "http://icondataset.org/standing-on-the-ground", "http://icondataset.org/cross", "http://icondataset.org/holding-with-the-right-hand", "http://icondataset.org/carrying-on-shoulders"], "in both": ["http://icondataset.org/man"]}, "http://icondataset.org/anteros": {"only not cf": ["http://icondataset.org/putto"], "only cf": ["http://icondataset.org/child", "http://icondataset.org/halo", "http://icondataset.org/tree", "http://icondataset.org/boy", "http://icondataset.org/fishing", "http://icondataset.org/tying"], "in both": ["http://icondataset.org/wings"]}, "http://icondataset.org/ganymede": {"only not cf": ["http://icondataset.org/cloth"], "only cf": ["http://icondataset.org/state-of-trance", "http://icondataset.org/immobility"], "in both": ["http://icondataset.org/man"]}, "http://icondataset.org/laocoon": {"only not cf": ["http://icondataset.org/despair", "http://icondataset.org/pathos", "http://icondataset.org/wiggling-out-of-serpents"], "only cf": ["http://icondataset.org/clothes"], "in both": ["http://icondataset.org/man", "http://icondataset.org/bear"]}, "http://icondataset.org/christ-as-a-child": {"only not cf": [], "only cf": [], "in both": ["http://icondataset.org/child"]}, "http://icondataset.org/marine-snakes": {"only not cf": ["http://icondataset.org/grabbing"], "only cf": ["http://icondataset.org/water"], "in both": ["http://icondataset.org/serpent"]}, "http://icondataset.org/perseus": {"only not cf": ["http://icondataset.org/running", "http://icondataset.org/lifting-with-one-hand", "http://icondataset.org/cloth", "http://icondataset.org/grace", "http://icondataset.org/cutten-head"], "only cf": [], "in both": ["http://icondataset.org/man", "http://icondataset.org/sword", "http://icondataset.org/wings-at-the-heels"]}, "http://icondataset.org/antiphas-son-of-laoocoon": {"only not cf": ["http://icondataset.org/despair", "http://icondataset.org/cloth", "http://icondataset.org/wiggling-out-of-serpents"], "only cf": ["http://icondataset.org/clothes"], "in both": ["http://icondataset.org/boy"]}, "http://icondataset.org/mary": {"only not cf": ["http://icondataset.org/dais", "http://icondataset.org/sketch-of-a-human-figure"], "only cf": ["http://icondataset.org/clothes", "http://icondataset.org/mantle", "http://icondataset.org/statue-of-a-woman", "http://icondataset.org/book", "http://icondataset.org/halo", "http://icondataset.org/girl", "http://icondataset.org/face", "http://icondataset.org/smiling", "http://icondataset.org/holding-a-book"], "in both": ["http://icondataset.org/woman"]}, "http://icondataset.org/venus": {"only not cf": ["http://icondataset.org/touching-breast", "http://icondataset.org/veil", "http://icondataset.org/seashell", "http://icondataset.org/holding-a-wreath", "http://icondataset.org/earring", "http://icondataset.org/tiara", "http://icondataset.org/knotted-ribbon-bracelet", "http://icondataset.org/rose-petal", "http://icondataset.org/belt"], "only cf": ["http://icondataset.org/pensively", "http://icondataset.org/clothes", "http://icondataset.org/holding-a-rose-to-her-face", "http://icondataset.org/sea-goose", "http://icondataset.org/crown", "http://icondataset.org/arrow", "http://icondataset.org/slate", "http://icondataset.org/lady", "http://icondataset.org/dove", "http://icondataset.org/sea-goose-with-a-fish-tail", "http://icondataset.org/holding-on-her-lap", "http://icondataset.org/emerging-from-the-water", "http://icondataset.org/glass-sphere"], "in both": ["http://icondataset.org/woman", "http://icondataset.org/holding-with-a-hand", "http://icondataset.org/rose"]}, "http://icondataset.org/david": {"only not cf": ["http://icondataset.org/man"], "only cf": ["http://icondataset.org/victorious", "http://icondataset.org/drapery", "http://icondataset.org/boy", "http://icondataset.org/pathos", "http://icondataset.org/agitated-movement"], "in both": []}, "http://icondataset.org/thymbraeus-son-of-laoocoon": {"only not cf": ["http://icondataset.org/despair", "http://icondataset.org/cloth", "http://icondataset.org/wiggling-out-of-serpents"], "only cf": ["http://icondataset.org/clothes"], "in both": ["http://icondataset.org/boy"]}, "http://icondataset.org/pluto": {"only not cf": ["http://icondataset.org/figure"], "only cf": ["http://icondataset.org/lending-both-hands-to-a-woman", "http://icondataset.org/man", "http://icondataset.org/jar", "http://icondataset.org/courteous-attitude", "http://icondataset.org/crown", "http://icondataset.org/pluto", "http://icondataset.org/sceptre", "http://icondataset.org/holding-with-the-left-hand", "http://icondataset.org/cart", "http://icondataset.org/triple-throated-cerberus", "http://icondataset.org/holding-with-the-right-hand", "http://icondataset.org/knight", "http://icondataset.org/grabbing-and-lifting-a-woman", "http://icondataset.org/armor", "http://icondataset.org/force"], "in both": []}, "http://icondataset.org/proserpina": {"only not cf": [], "only cf": ["http://icondataset.org/preserpine", "http://icondataset.org/sitting-down", "http://icondataset.org/lending-one-hand-to-a-man", "http://icondataset.org/backward-gaze", "http://icondataset.org/gathering-flowers", "http://icondataset.org/crying", "http://icondataset.org/flowers", "http://icondataset.org/court-dress", "http://icondataset.org/raising-arms-upwards"], "in both": ["http://icondataset.org/woman"]}, "http://icondataset.org/satyr": {"only not cf": [], "only cf": ["http://icondataset.org/woman-with-goat-legs", "http://icondataset.org/human-baby-with-animal-legs"], "in both": ["http://icondataset.org/human-figure-with-animal-legs"]}, "http://icondataset.org/eve": {"only not cf": [], "only cf": [], "in both": ["http://icondataset.org/woman"]}, "http://icondataset.org/saturn": {"only not cf": [], "only cf": ["http://icondataset.org/despair", "http://icondataset.org/clothes", "http://icondataset.org/helmet", "http://icondataset.org/sitting-on", "http://icondataset.org/soldier", "http://icondataset.org/throne", "http://icondataset.org/crown", "http://icondataset.org/veil", "http://icondataset.org/gloomy", "http://icondataset.org/spade", "http://icondataset.org/cloth", "http://icondataset.org/scythe", "http://icondataset.org/support-oneself-with", "http://icondataset.org/crutch", "http://icondataset.org/sickle", "http://icondataset.org/king", "http://icondataset.org/wooden-leg", "http://icondataset.org/dragon-biting-its-tail"], "in both": ["http://icondataset.org/man", "http://icondataset.org/wings", "http://icondataset.org/bear"]}, "http://icondataset.org/lapiths": {"only not cf": ["http://icondataset.org/people"], "only cf": ["http://icondataset.org/stick", "http://icondataset.org/man"], "in both": []}, "http://icondataset.org/companion-of-serapis": {"only not cf": [], "only cf": ["http://icondataset.org/three-headed-serpent", "http://icondataset.org/man", "http://icondataset.org/modius", "http://icondataset.org/sceptre"], "in both": ["http://icondataset.org/head-of-a-lion", "http://icondataset.org/three-headed-figure", "http://icondataset.org/serpent", "http://icondataset.org/head-of-a-dog", "http://icondataset.org/twisting-around", "http://icondataset.org/head-of-a-wolf"]}, "http://icondataset.org/blindfold-cupid": {"only not cf": ["http://icondataset.org/band", "http://icondataset.org/running", "http://icondataset.org/spear", "http://icondataset.org/horse", "http://icondataset.org/standing-on-a-horse"], "only cf": ["http://icondataset.org/talon", "http://icondataset.org/sphere", "http://icondataset.org/putto", "http://icondataset.org/throne", "http://icondataset.org/string-of-hearts", "http://icondataset.org/sleeping", "http://icondataset.org/crown-of-roses", "http://icondataset.org/standing-on", "http://icondataset.org/hearts", "http://icondataset.org/natural-landscape", "http://icondataset.org/snuggling-in-her-lap"], "in both": ["http://icondataset.org/griffon-claws", "http://icondataset.org/wings", "http://icondataset.org/child", "http://icondataset.org/arrow", "http://icondataset.org/boy", "http://icondataset.org/bandage", "http://icondataset.org/bow"]}, "http://icondataset.org/phaeton": {"only not cf": [], "only cf": [], "in both": ["http://icondataset.org/man", "http://icondataset.org/falling-off"]}, "http://icondataset.org/cupid": {"only not cf": ["http://icondataset.org/playful-attitude", "http://icondataset.org/holding-a-wreath"], "only cf": ["http://icondataset.org/young", "http://icondataset.org/man", "http://icondataset.org/flying", "http://icondataset.org/wreath", "http://icondataset.org/sleeping", "http://icondataset.org/taking-aim", "http://icondataset.org/intense-devotion", "http://icondataset.org/leaning-upon", "http://icondataset.org/griffon-claws", "http://icondataset.org/stirring-water", "http://icondataset.org/rose", "http://icondataset.org/fire", "http://icondataset.org/string-of-hearts", "http://icondataset.org/bandage", "http://icondataset.org/lappets", "http://icondataset.org/boots", "http://icondataset.org/court-dress", "http://icondataset.org/ribbon", "http://icondataset.org/grabbing-with-one-hand", "http://icondataset.org/holding-with-a-hand", "http://icondataset.org/woman", "http://icondataset.org/crown", "http://icondataset.org/horse", "http://icondataset.org/child", "http://icondataset.org/shooting-an-arrow", "http://icondataset.org/removing", "http://icondataset.org/girl", "http://icondataset.org/fishing", "http://icondataset.org/leaning-on-her-shoulder", "http://icondataset.org/myrtle-wreath", "http://icondataset.org/standing-on-a-horse"], "in both": ["http://icondataset.org/wings", "http://icondataset.org/mantle", "http://icondataset.org/putto", "http://icondataset.org/arrow", "http://icondataset.org/boy", "http://icondataset.org/torch", "http://icondataset.org/bow"]}, "http://icondataset.org/mercurys-winged-sandals": {"only not cf": [], "only cf": ["http://icondataset.org/bird"], "in both": ["http://icondataset.org/wings-at-the-heels"]}, "http://icondataset.org/medusas-head": {"only not cf": ["http://icondataset.org/drops-of-blood"], "only cf": ["http://icondataset.org/caput-meduse"], "in both": ["http://icondataset.org/serpent-locks", "http://icondataset.org/cutten-head"]}, "http://icondataset.org/luxury": {"only not cf": ["http://icondataset.org/embracing", "http://icondataset.org/lover"], "only cf": ["http://icondataset.org/woman"], "in both": []}, "http://icondataset.org/the-constellation-perseus": {"only not cf": ["http://icondataset.org/wings-at-the-heels", "http://icondataset.org/running", "http://icondataset.org/cloth", "http://icondataset.org/grace", "http://icondataset.org/drops-of-blood"], "only cf": ["http://icondataset.org/terrifying-expression", "http://icondataset.org/beard", "http://icondataset.org/gown", "http://icondataset.org/caput-algol", "http://icondataset.org/lifting-one-hand", "http://icondataset.org/caput-meduse", "http://icondataset.org/constellation"], "in both": ["http://icondataset.org/man", "http://icondataset.org/grabbing-with-one-hand", "http://icondataset.org/sword", "http://icondataset.org/serpent-locks", "http://icondataset.org/lifting-with-one-hand", "http://icondataset.org/cutten-head"]}, "http://icondataset.org/faith": {"only not cf": ["http://icondataset.org/woman"], "only cf": ["http://icondataset.org/joyful-excitement", "http://icondataset.org/basket-with-roses", "http://icondataset.org/raising", "http://icondataset.org/glancing-heavenward", "http://icondataset.org/figure"], "in both": []}, "http://icondataset.org/blind-night": {"only not cf": ["http://icondataset.org/figure", "http://icondataset.org/veil", "http://icondataset.org/covering-her-eyes"], "only cf": ["http://icondataset.org/bandage"], "in both": ["http://icondataset.org/woman"]}, "http://icondataset.org/platonic-love": {"only not cf": ["http://icondataset.org/torch", "http://icondataset.org/boy"], "only cf": ["http://icondataset.org/arrow", "http://icondataset.org/child"], "in both": ["http://icondataset.org/wings"]}, "http://icondataset.org/day": {"only not cf": ["http://icondataset.org/figure"], "only cf": ["http://icondataset.org/man"], "in both": []}, "http://icondataset.org/truth": {"only not cf": ["http://icondataset.org/despair"], "only cf": ["http://icondataset.org/child", "http://icondataset.org/removing", "http://icondataset.org/girl", "http://icondataset.org/disgust", "http://icondataset.org/curtain"], "in both": ["http://icondataset.org/woman"]}, "http://icondataset.org/chastity": {"only not cf": ["http://icondataset.org/lilium"], "only cf": ["http://icondataset.org/maiden", "http://icondataset.org/arrow", "http://icondataset.org/covering-herself"], "in both": ["http://icondataset.org/woman"]}, "http://icondataset.org/phaeton-the-presumptuous": {"only not cf": [], "only cf": [], "in both": ["http://icondataset.org/man", "http://icondataset.org/falling-off"]}, "http://icondataset.org/four-wings-four-seasons": {"only not cf": [], "only cf": [], "in both": ["http://icondataset.org/wings"]}, "http://icondataset.org/fall-of-phaeton-fate-of-every-temerarius": {"only not cf": ["http://icondataset.org/sun", "http://icondataset.org/cloud"], "only cf": ["http://icondataset.org/hurling", "http://icondataset.org/group-of-figures", "http://icondataset.org/chariot", "http://icondataset.org/thunderbolt", "http://icondataset.org/eagle"], "in both": ["http://icondataset.org/man", "http://icondataset.org/falling-off", "http://icondataset.org/horse"]}, "http://icondataset.org/slave-human-soul-in-so-far-as-it-is-devoid-of-freedom": {"only not cf": ["http://icondataset.org/slave"], "only cf": ["http://icondataset.org/statue-of-a-slave"], "in both": []}}